bioeval/__init__.py
bioeval/core.py
bioeval/utils.py
bioeval-1.1.14.dist-info/LICENSE
bioeval-1.1.14.dist-info/METADATA
bioeval-1.1.14.dist-info/WHEEL
bioeval-1.1.14.dist-info/top_level.txt
bioeval-1.1.14.dist-info/zip-safe
bioeval-1.1.14.dist-info/RECORD
