Metadata-Version: 2.1
Name: bioeval
Version: 1.1.14
Summary: BIO and BEISO evaluation library
Home-page: https://github.com/savkov/bioeval
Author: Sasho Savkov
Author-email: me@sasho.io
License: MIT
Platform: UNKNOWN
Classifier: Intended Audience :: Science/Research
Classifier: Operating System :: Unix
Classifier: License :: OSI Approved :: MIT License
Classifier: Programming Language :: Python
Classifier: Programming Language :: Python :: 3
Classifier: Programming Language :: Python :: 3.2
Classifier: Programming Language :: Python :: 3.3
Classifier: Programming Language :: Python :: 3.4
Classifier: Programming Language :: Python :: 3.5
Classifier: Programming Language :: Python :: 3.6
Classifier: Topic :: Scientific/Engineering
Requires-Dist: iterpipes3 (==0.4)
Requires-Dist: numpy (==1.16.4)
